api.py
strava_cz_api-1.2.dist-info/licenses/LICENSE
strava_cz_api-1.2.dist-info/METADATA
strava_cz_api-1.2.dist-info/WHEEL
strava_cz_api-1.2.dist-info/top_level.txt
strava_cz_api-1.2.dist-info/RECORD
