Metadata-Version: 2.4
Name: strava.cz_api
Version: 1.2
Summary: Rest API for strava.cz.
Author-email: Matěj Adamec <kralyk@kralyk.dev>
Requires-Python: >=3.8
License-File: LICENSE
Dynamic: license-file
